make_templates/README.md
make_templates/__init__.py
make_templates/analyzer.py
make_templates/main.py
make_templates/tree.py
make_templates/parser/IOLexer.py
make_templates/parser/IOParser.py
make_templates/parser/IOParserVisitor.py
make_templates/parser/__init__.py
make_templates/targets/__init__.py
make_templates/targets/c.py
make_templates/targets/cpp.py
make_templates/targets/cs.py
make_templates/targets/go.py
make_templates/targets/html.py
make_templates/targets/java.py
make_templates/targets/md.py
make_templates/targets/pas.py
make_templates/targets/py.py
make_templates/targets/tex.py
make_templates/targets/vb.py
make_templates-0.2.13.dist-info/LICENSE
make_templates-0.2.13.dist-info/METADATA
make_templates-0.2.13.dist-info/WHEEL
make_templates-0.2.13.dist-info/entry_points.txt
make_templates-0.2.13.dist-info/top_level.txt
make_templates-0.2.13.dist-info/RECORD
