Metadata-Version: 2.1
Name: make-templates
Version: 0.2.13
Summary: Tool to produce templates for IOI-style tasks from an input/output description.
Home-page: http://olinfo.it
Author: Giorgio Audrito
Author-email: giorgio.audrito@unito.it
License: BSD
License-File: LICENSE
Requires-Dist: antlr4-python3-runtime==4.13.1
Requires-Dist: pyyaml
